flomo_cli/__init__.py
flomo_cli/client.py
flomo_cli/const.py
flomo_cli/display.py
flomo_cli/entry.py
flomo_cli/key_manager.py
flomo_cli/url_store.py
flomo_cli/utils.py
flomo_cli-0.1.2.dist-info/LICENSE
flomo_cli-0.1.2.dist-info/METADATA
flomo_cli-0.1.2.dist-info/WHEEL
flomo_cli-0.1.2.dist-info/entry_points.txt
flomo_cli-0.1.2.dist-info/RECORD
