Metadata-Version: 2.3
Name: flomo-cli
Version: 0.1.2
Summary: Create flomo memo from your terminal
Author: Antarx
Author-email: liangyi@bupt.edu.cn
Requires-Python: >=3.12
Classifier: Programming Language :: Python :: 3
Classifier: Programming Language :: Python :: 3.12
Classifier: Programming Language :: Python :: 3.13
Requires-Dist: prompt-toolkit (>=3.0.51,<4.0.0)
Requires-Dist: requests (>=2.32.4,<3.0.0)
Requires-Dist: rich (>=14.1.0,<15.0.0)
Requires-Dist: toml (>=0.10.2,<0.11.0)
